build/lib/build/lib/build/lib/build/lib/build/lib/build/lib/build/lib/eops/__init__.py
build/lib/build/lib/build/lib/build/lib/build/lib/build/lib/build/lib/eops/cli.py
build/lib/build/lib/build/lib/build/lib/build/lib/build/lib/build/lib/eops/instruments.py
build/lib/build/lib/build/lib/build/lib/build/lib/build/lib/build/lib/eops/models.py
build/lib/build/lib/build/lib/build/lib/build/lib/build/lib/build/lib/eops/worker.py
build/lib/build/lib/build/lib/build/lib/build/lib/build/lib/eops/__init__.py
build/lib/build/lib/build/lib/build/lib/build/lib/build/lib/eops/cli.py
build/lib/build/lib/build/lib/build/lib/build/lib/build/lib/eops/instruments.py
build/lib/build/lib/build/lib/build/lib/build/lib/build/lib/eops/models.py
build/lib/build/lib/build/lib/build/lib/build/lib/build/lib/eops/worker.py
build/lib/build/lib/build/lib/build/lib/build/lib/build/lib/eops/core/backtester.py
build/lib/build/lib/build/lib/build/lib/build/lib/build/lib/eops/core/engine.py
build/lib/build/lib/build/lib/build/lib/build/lib/build/lib/eops/core/event.py
build/lib/build/lib/build/lib/build/lib/build/lib/build/lib/eops/core/exchange.py
build/lib/build/lib/build/lib/build/lib/build/lib/build/lib/eops/core/portfolio.py
build/lib/build/lib/build/lib/build/lib/build/lib/build/lib/eops/core/sim_exchange.py
build/lib/build/lib/build/lib/build/lib/build/lib/build/lib/eops/core/strategy.py
build/lib/build/lib/build/lib/build/lib/build/lib/build/lib/eops/core/backtest/__init__.py
build/lib/build/lib/build/lib/build/lib/build/lib/build/lib/eops/core/backtest/executor.py
build/lib/build/lib/build/lib/build/lib/build/lib/build/lib/eops/core/backtest/updater.py
build/lib/build/lib/build/lib/build/lib/build/lib/build/lib/eops/core/handler/__init__.py
build/lib/build/lib/build/lib/build/lib/build/lib/build/lib/eops/core/handler/decider.py
build/lib/build/lib/build/lib/build/lib/build/lib/build/lib/eops/core/handler/event_handler.py
eops-0.1.3.dist-info/licenses/LICENSE
eops-0.1.3.dist-info/METADATA
eops-0.1.3.dist-info/WHEEL
eops-0.1.3.dist-info/entry_points.txt
eops-0.1.3.dist-info/top_level.txt
eops-0.1.3.dist-info/RECORD
